{"raw": {"records": [{"_status": {"code": 200, "text": "OK", "request_id": "2013b90d-31c7-4d70-8dc9-e89c1285a64b"}, "_id": "6c1e9408-5e71-439b-898d-9f8ec76d86cc", "_width": 1500, "_height": 2000, "_objects": [{"name": "Clothing", "id": "8e6cf45d-d416-4560-a89a-1b83b80e003b", "bound_box": [124, 686, 1223, 1988], "prob": 0.9361949563026428, "area": 0.476966, "Top Category": "Clothing", "_tags": {"Category": [{"prob": 0.99823, "name": "Clothing/Upper", "id": "fe984081-9c79-44ed-bf48-6e0075066e17"}], "Subcategory": [{"prob": 0.98558, "name": "t-shirts", "id": "769f678b-123e-42fd-acfc-aa64328f6d31"}], "Color": [{"prob": 0.96249, "name": "dark blue and navy", "id": "bc0d83a6-98ce-4e20-8660-c44beafbc70d"}], "Gender": [{"prob": 0.98609, "name": "men", "id": "937c8952-89d5-4406-99f8-f82c1b0c71c6"}], "Neckline": [{"prob": 0.95524, "name": "crew", "id": "777ff42a-2183-4ba7-bccd-07bdced516bf"}], "Sleeves": [{"prob": 0.99894, "name": "short sleeves", "id": "5e12bdb6-b8f8-4734-9966-d09d10818ce9"}], "Material": [{"prob": 0.64408, "name": "knitwear", "id": "38250863-933f-41c3-a9f9-412607ae464a"}], "Style": [{"prob": 0.89096, "name": "casual", "id": "f7c9e44d-1a33-46e8-94d5-0f7a7b3a274e"}], "Age": [{"prob": 0.99575, "name": "adult", "id": "464f18b8-e61b-4f95-afe6-48b3a8db26ab"}], "Design": [{"prob": 0.86729, "name": "plain", "id": "ef9751c5-dfb9-4d36-9691-359865f8bb92"}], "Top Category": [{"id": "13052be8-2cc7-48e4-a782-a00d658f997c", "name": "Clothing", "prob": 1.0}]}, "_tags_simple": ["plain", "dark blue and navy", "knitwear", "Clothing", "men", "t-shirts", "adult", "short sleeves", "Clothing/Upper", "crew", "casual"], "Category": "Clothing/Upper"}]}], "version": "2022-02-23 09:30:33.780947+00:00", "model_format": "", "status": {"code": 200, "text": "OK", "request_id": "2013b90d-31c7-4d70-8dc9-e89c1285a64b", "proc_id": "c89eb1b6-7c47-4753-b748-3c9bce02fac8"}, "statistics": {"processing time": 0.6975481510162354}}, "image": "https://fashion.coveodemo.com//images\\cn12150916.jpg", "clean": {"Clothing/Upper": {"Tags": ["plain", "dark blue and navy", "knitwear", "Clothing", "men", "t-shirts", "adult", "short sleeves", "Clothing/Upper", "crew", "casual"], "Category": "Clothing/Upper", "Subcategory": "t-shirts", "Color": "dark blue and navy", "Gender": "men", "Neckline": "crew", "Sleeves": "short sleeves", "Material": "knitwear", "Style": "casual", "Age": "adult", "Design": "plain", "Top Category": "Clothing", "ProductTitle": "Casual Dark Blue And Navy Knitwear T-Shirts", "price": 23, "brand": "Banana Republic"}}}