{"raw": {"records": [{"_status": {"code": 200, "text": "OK", "request_id": "ea2d9f80-ef3b-4052-9e54-ea74d76f9ddc"}, "_id": "4bde09b4-6688-4709-9400-54229049688e", "_width": 1245, "_height": 1659, "_objects": []}], "version": "2022-02-23 09:30:33.780947+00:00", "model_format": "", "status": {"code": 200, "text": "OK", "request_id": "ea2d9f80-ef3b-4052-9e54-ea74d76f9ddc", "proc_id": "c89eb1b6-7c47-4753-b748-3c9bce02fac8"}, "statistics": {"processing time": 0.39592599868774414}}, "image": "https://fashion.coveodemo.com//images\\cn13588310.jpg", "clean": {}, "pixyle": {"status": "OK", "method": "autotag/image", "result": [{"product_id": "5514853", "category": "sweatshirt", "pixyle_detected_category": "sweatshirt", "verified": false, "score": 0.98, "product_coordinates": {"x_min": 0, "y_min": 19, "x_max": 1115, "y_max": 1154}, "detected_attributes_types": [{"attribute_type": "sweatshirt_type", "attributes": {"correct": [{"attribute": "everyday-sweatshirt", "score": 0.99999}], "all": [{"attribute": "everyday-sweatshirt", "score": 0.99999}, {"attribute": "full-zip", "score": 1e-05}]}}, {"attribute_type": "neckline_type", "attributes": {"correct": [{"attribute": "crew-neck", "score": 0.48616}], "all": [{"attribute": "crew-neck", "score": 0.48616}, {"attribute": "round-neck", "score": 0.44484}, {"attribute": "high-neck", "score": 0.04724}, {"attribute": "v-neck", "score": 0.01248}, {"attribute": "turtle-neck", "score": 0.00416}, {"attribute": "boat-neck", "score": 0.00175}, {"attribute": "cowl-neck", "score": 0.00077}, {"attribute": "shoulder-off", "score": 0.00072}, {"attribute": "one-shoulder", "score": 0.0004}, {"attribute": "shawl-collar", "score": 0.00031}, {"attribute": "sweetheart-neck", "score": 0.00029}, {"attribute": "square-neck", "score": 0.00025}, {"attribute": "round-v-neck", "score": 0.00024}, {"attribute": "polo", "score": 0.00018}, {"attribute": "button-down", "score": 7e-05}, {"attribute": "hooded", "score": 5e-05}, {"attribute": "notched-collar", "score": 4e-05}, {"attribute": "cutaway", "score": 4e-05}, {"attribute": "grandad", "score": 0.0}]}}, {"attribute_type": "tops_fit", "attributes": {"correct": [{"attribute": "bodycon-tops", "score": 0.86871}], "all": [{"attribute": "bodycon-tops", "score": 0.86871}, {"attribute": "fitted-tops", "score": 0.09684}, {"attribute": "regular-fit-tops", "score": 0.0174}, {"attribute": "oversized-tops", "score": 0.01706}]}}, {"attribute_type": "tops_length", "attributes": {"correct": [{"attribute": "cropped", "score": 0.93035}], "all": [{"attribute": "cropped", "score": 0.93035}, {"attribute": "long", "score": 0.04795}, {"attribute": "short", "score": 0.01825}, {"attribute": "thigh-length", "score": 0.00345}]}}, {"attribute_type": "sleeve_length", "attributes": {"correct": [{"attribute": "sleeveless", "score": 0.65823}], "all": [{"attribute": "sleeveless", "score": 0.65823}, {"attribute": "long-sleeve", "score": 0.16979}, {"attribute": "straps", "score": 0.10495}, {"attribute": "short-sleeve", "score": 0.06102}, {"attribute": "3-4-sleeve", "score": 0.00568}, {"attribute": "strapless", "score": 0.00034}]}}, {"attribute_type": "sleeve_type", "attributes": {"correct": [], "all": [{"attribute": "dolman-sleeve", "score": 0.0}, {"attribute": "flutter-sleeve", "score": 0.0}, {"attribute": "flare-sleeve", "score": 0.0}, {"attribute": "puff-sleeve", "score": 0.0}, {"attribute": "straight-sleeve", "score": 0.0}]}}, {"attribute_type": "colors", "attributes": {"correct": [{"attribute": "gray", "score": 0.67776}], "all": [{"attribute": "gray", "score": 0.67776}, {"attribute": "black", "score": 0.19361}, {"attribute": "multicolor", "score": 0.11129}, {"attribute": "navy", "score": 0.00942}, {"attribute": "brown", "score": 0.00302}, {"attribute": "silver", "score": 0.00262}, {"attribute": "white", "score": 0.00049}, {"attribute": "purple", "score": 0.00047}, {"attribute": "gold", "score": 0.00039}, {"attribute": "khaki", "score": 0.00037}, {"attribute": "green", "score": 0.00014}, {"attribute": "lavander", "score": 8e-05}, {"attribute": "bordeaux", "score": 7e-05}, {"attribute": "emerald-green", "score": 6e-05}, {"attribute": "blue", "score": 4e-05}, {"attribute": "neon", "score": 3e-05}, {"attribute": "beige", "score": 3e-05}, {"attribute": "pink", "score": 2e-05}, {"attribute": "red", "score": 2e-05}, {"attribute": "magenta", "score": 1e-05}, {"attribute": "orange", "score": 1e-05}, {"attribute": "mustard", "score": 1e-05}, {"attribute": "pastel", "score": 1e-05}, {"attribute": "coral", "score": 0.0}, {"attribute": "yellow", "score": 0.0}, {"attribute": "turquoise", "score": 0.0}, {"attribute": "ecru", "score": 0.0}, {"attribute": "canyon-rose", "score": 0.0}, {"attribute": "copper", "score": 0.0}, {"attribute": "mint", "score": 0.0}]}}, {"attribute_type": "pattern", "attributes": {"correct": [{"attribute": "marled", "score": 0.98059}], "all": [{"attribute": "marled", "score": 0.98059}, {"attribute": "varsity-striped", "score": 0.00556}, {"attribute": "glitter", "score": 0.00378}, {"attribute": "stripes", "score": 0.00202}, {"attribute": "horizontal-stripes", "score": 0.00148}, {"attribute": "text-print", "score": 0.00134}, {"attribute": "vertical-stripes", "score": 0.00112}, {"attribute": "plain", "score": 0.00092}, {"attribute": "herringbone", "score": 0.00072}, {"attribute": "diagonal-stripes", "score": 0.0005}, {"attribute": "windowpane", "score": 0.0004}, {"attribute": "glen-check", "score": 0.00032}, {"attribute": "bird's-eye", "score": 0.00031}, {"attribute": "chevron", "score": 0.00021}, {"attribute": "ombre", "score": 0.00014}, {"attribute": "harlequin", "score": 0.00012}, {"attribute": "gingham", "score": 7e-05}, {"attribute": "dots", "score": 6e-05}, {"attribute": "abstract", "score": 6e-05}, {"attribute": "quilted", "score": 4e-05}, {"attribute": "geometric", "score": 4e-05}, {"attribute": "logo-print", "score": 3e-05}, {"attribute": "tartan", "score": 2e-05}, {"attribute": "greek-key", "score": 1e-05}, {"attribute": "houndstooth", "score": 1e-05}, {"attribute": "checkerboard", "score": 1e-05}, {"attribute": "camo", "score": 1e-05}, {"attribute": "net", "score": 1e-05}, {"attribute": "paisley", "score": 1e-05}, {"attribute": "graph-check", "score": 1e-05}, {"attribute": "3d-print", "score": 1e-05}, {"attribute": "bleached", "score": 1e-05}, {"attribute": "floral", "score": 1e-05}, {"attribute": "shapes", "score": 1e-05}, {"attribute": "arrow-print", "score": 0.0}, {"attribute": "feathers", "score": 0.0}, {"attribute": "scale", "score": 0.0}, {"attribute": "brocade", "score": 0.0}, {"attribute": "retro", "score": 0.0}, {"attribute": "zebra", "score": 0.0}, {"attribute": "damask", "score": 0.0}, {"attribute": "natural", "score": 0.0}, {"attribute": "brush-stroke", "score": 0.0}, {"attribute": "sequined", "score": 0.0}, {"attribute": "fruits", "score": 0.0}, {"attribute": "crocodile-skin", "score": 0.0}, {"attribute": "snake-skin", "score": 0.0}, {"attribute": "animal-print", "score": 0.0}, {"attribute": "animals", "score": 0.0}, {"attribute": "leaf", "score": 0.0}]}}, {"attribute_type": "material", "attributes": {"correct": [], "all": [{"attribute": "teddy", "score": 0.0}, {"attribute": "cotton", "score": 0.0}, {"attribute": "knitted", "score": 0.0}, {"attribute": "linen", "score": 0.0}, {"attribute": "fur", "score": 0.0}, {"attribute": "leather", "score": 0.0}, {"attribute": "suede", "score": 0.0}, {"attribute": "tweed", "score": 0.0}, {"attribute": "velvet", "score": 0.0}, {"attribute": "satin", "score": 0.0}, {"attribute": "denim", "score": 0.0}, {"attribute": "canvas", "score": 0.0}, {"attribute": "chiffon", "score": 0.0}, {"attribute": "tulle", "score": 0.0}, {"attribute": "fuzzy", "score": 0.0}, {"attribute": "corduroy", "score": 0.0}, {"attribute": "silk", "score": 0.0}, {"attribute": "mesh", "score": 0.0}, {"attribute": "faux-fur", "score": 0.0}, {"attribute": "woven", "score": 0.0}, {"attribute": "crochet", "score": 0.0}, {"attribute": "lace", "score": 0.0}, {"attribute": "crinkled", "score": 0.0}]}}, {"attribute_type": "more_attributes", "attributes": {"correct": [], "all": [{"attribute": "draped", "score": 0.0}, {"attribute": "bib", "score": 0.0}, {"attribute": "open-back", "score": 0.0}, {"attribute": "pom-poms", "score": 0.0}, {"attribute": "wrap", "score": 0.0}, {"attribute": "slit", "score": 0.0}, {"attribute": "keyhole", "score": 0.0}, {"attribute": "lace-up", "score": 0.0}, {"attribute": "embroidered", "score": 0.0}, {"attribute": "ruched", "score": 0.0}, {"attribute": "cargo", "score": 0.0}, {"attribute": "knotted", "score": 0.0}, {"attribute": "stones", "score": 0.0}, {"attribute": "chains", "score": 0.0}, {"attribute": "fringe", "score": 0.0}, {"attribute": "ruffled", "score": 0.0}, {"attribute": "studs_and_spikes", "score": 0.0}, {"attribute": "pleated", "score": 0.0}, {"attribute": "pearls", "score": 0.0}, {"attribute": "jewels", "score": 0.0}, {"attribute": "ripped", "score": 0.0}, {"attribute": "drawstring", "score": 0.0}, {"attribute": "belted", "score": 0.0}, {"attribute": "zipper", "score": 0.0}, {"attribute": "shoelaces", "score": 0.0}, {"attribute": "buttons", "score": 0.0}, {"attribute": "metalic", "score": 0.0}]}}, {"attribute_type": "style", "attributes": {"correct": [{"attribute": "sporty", "score": 0.82118}], "all": [{"attribute": "sporty", "score": 0.82118}, {"attribute": "casual", "score": 0.17577}, {"attribute": "modest", "score": 0.00305}, {"attribute": "bohemian", "score": 0.0}, {"attribute": "business", "score": 0.0}, {"attribute": "feminine", "score": 0.0}, {"attribute": "minimalism", "score": 0.0}, {"attribute": "sexy", "score": 0.0}, {"attribute": "sophisticated", "score": 0.0}, {"attribute": "punk", "score": 0.0}]}}, {"attribute_type": "occasion", "attributes": {"correct": [{"attribute": "sport", "score": 0.79851}], "all": [{"attribute": "sport", "score": 0.79851}, {"attribute": "casual", "score": 0.17092}, {"attribute": "home-lounge", "score": 0.02761}, {"attribute": "winter", "score": 0.00296}, {"attribute": "formal", "score": 0.0}, {"attribute": "semi-formal", "score": 0.0}, {"attribute": "office", "score": 0.0}, {"attribute": "nightout", "score": 0.0}, {"attribute": "dating", "score": 0.0}, {"attribute": "beach", "score": 0.0}, {"attribute": "summer", "score": 0.0}]}}]}], "meta": {"counter_products": 1}}}