{"raw": {"records": [{"_status": {"code": 200, "text": "OK", "request_id": "741f7acc-f8e3-4bfa-b67b-9b60b58a303d"}, "_id": "e3c7fe74-f1b9-4913-a859-187c928404c4", "_width": 1500, "_height": 2000, "_objects": [{"name": "Clothing", "id": "8e6cf45d-d416-4560-a89a-1b83b80e003b", "bound_box": [294, 475, 1196, 1997], "prob": 0.9240456223487854, "area": 0.45761466666666667, "Top Category": "Clothing", "_tags": {"Category": [{"prob": 0.99729, "name": "Clothing/Upper", "id": "fe984081-9c79-44ed-bf48-6e0075066e17"}], "Subcategory": [{"prob": 0.79971, "name": "t-shirts", "id": "769f678b-123e-42fd-acfc-aa64328f6d31"}, {"prob": 0.38773, "name": "polo-shirts", "id": "bf237f04-0f14-41a0-83b1-5a188eb9e65a"}], "Color": [{"prob": 0.97133, "name": "multicolor", "id": "d2b6c02c-f84b-444a-b4cd-bc2d49b8e529"}], "Gender": [{"prob": 0.98835, "name": "men", "id": "937c8952-89d5-4406-99f8-f82c1b0c71c6"}], "Neckline": [{"prob": 0.73245, "name": "crew", "id": "777ff42a-2183-4ba7-bccd-07bdced516bf"}], "Sleeves": [{"prob": 0.99793, "name": "short sleeves", "id": "5e12bdb6-b8f8-4734-9966-d09d10818ce9"}], "Material": [{"prob": 0.55797, "name": "knitwear", "id": "38250863-933f-41c3-a9f9-412607ae464a"}], "Style": [{"prob": 0.62231, "name": "casual", "id": "f7c9e44d-1a33-46e8-94d5-0f7a7b3a274e"}, {"prob": 0.35525, "name": "smart casual", "id": "91de9876-f055-432c-b4c8-5a361c3910c9"}], "Age": [{"prob": 0.99783, "name": "adult", "id": "464f18b8-e61b-4f95-afe6-48b3a8db26ab"}], "Design": [{"prob": 0.64371, "name": "plain", "id": "ef9751c5-dfb9-4d36-9691-359865f8bb92"}], "Top Category": [{"id": "13052be8-2cc7-48e4-a782-a00d658f997c", "name": "Clothing", "prob": 1.0}]}, "_tags_simple": ["crew", "casual", "Clothing", "short sleeves", "men", "knitwear", "Clothing/Upper", "multicolor", "plain", "adult", "t-shirts"], "Category": "Clothing/Upper"}]}], "version": "2022-02-23 09:30:33.780947+00:00", "model_format": "", "status": {"code": 200, "text": "OK", "request_id": "741f7acc-f8e3-4bfa-b67b-9b60b58a303d", "proc_id": "cb1a5e4d-5af6-4b7b-90c6-26da391578ee"}, "statistics": {"processing time": 0.7062909603118896}}, "image": "https://fashion.coveodemo.com//images\\cn14107195.jpg", "clean": {"Clothing/Upper": {"Tags": ["crew", "casual", "Clothing", "short sleeves", "men", "knitwear", "Clothing/Upper", "multicolor", "plain", "adult", "t-shirts"], "Category": "Clothing/Upper", "Subcategory": "t-shirts;polo-shirts", "Color": "multicolor", "Gender": "men", "Neckline": "crew", "Sleeves": "short sleeves", "Material": "knitwear", "Style": "casual;smart casual", "Age": "adult", "Design": "plain", "Top Category": "Clothing", "ProductTitle": "Casual Multicolor Knitwear T-Shirts", "price": 16, "brand": "American Eagle"}}, "pixyle": {"status": "OK", "method": "autotag/image", "result": [{"product_id": "5515140", "category": "sportswear", "pixyle_detected_category": "sportswear", "verified": false, "score": 0.96, "product_coordinates": {"x_min": 271, "y_min": 475, "x_max": 1187, "y_max": 1947}, "detected_attributes_types": [{"attribute_type": "sportswear_type", "attributes": {"correct": [{"attribute": "sport-top", "score": 0.9144}], "all": [{"attribute": "sport-top", "score": 0.9144}, {"attribute": "running-shorts", "score": 0.05602}, {"attribute": "sport-shorts", "score": 0.02672}, {"attribute": "sport-bra", "score": 0.00286}]}}, {"attribute_type": "sleeve_length", "attributes": {"correct": [{"attribute": "short-sleeve", "score": 0.98234}], "all": [{"attribute": "short-sleeve", "score": 0.98234}, {"attribute": "long-sleeve", "score": 0.00866}, {"attribute": "3-4-sleeve", "score": 0.00744}, {"attribute": "strapless", "score": 0.00069}, {"attribute": "sleeveless", "score": 0.00059}, {"attribute": "straps", "score": 0.0003}]}}, {"attribute_type": "neckline_type", "attributes": {"correct": [{"attribute": "round-neck", "score": 0.2477}], "all": [{"attribute": "round-neck", "score": 0.2477}, {"attribute": "high-neck", "score": 0.17679}, {"attribute": "crew-neck", "score": 0.16126}, {"attribute": "polo", "score": 0.08803}, {"attribute": "cutaway", "score": 0.07586}, {"attribute": "hooded", "score": 0.0593}, {"attribute": "v-neck", "score": 0.04701}, {"attribute": "one-shoulder", "score": 0.03961}, {"attribute": "cowl-neck", "score": 0.02234}, {"attribute": "shawl-collar", "score": 0.01962}, {"attribute": "turtle-neck", "score": 0.01646}, {"attribute": "boat-neck", "score": 0.01605}, {"attribute": "notched-collar", "score": 0.00994}, {"attribute": "shoulder-off", "score": 0.00819}, {"attribute": "square-neck", "score": 0.00458}, {"attribute": "button-down", "score": 0.00378}, {"attribute": "round-v-neck", "score": 0.00221}, {"attribute": "sweetheart-neck", "score": 0.00124}, {"attribute": "grandad", "score": 0.0}]}}, {"attribute_type": "waist_type", "attributes": {"correct": [], "all": [{"attribute": "mid-waist", "score": 0.0}, {"attribute": "low-waist", "score": 0.0}, {"attribute": "high-waist", "score": 0.0}]}}, {"attribute_type": "colors", "attributes": {"correct": [{"attribute": "bordeaux", "score": 0.89477}], "all": [{"attribute": "bordeaux", "score": 0.89477}, {"attribute": "multicolor", "score": 0.06288}, {"attribute": "black", "score": 0.01548}, {"attribute": "gray", "score": 0.01435}, {"attribute": "white", "score": 0.00492}, {"attribute": "magenta", "score": 0.00141}, {"attribute": "red", "score": 0.00107}, {"attribute": "pink", "score": 0.00097}, {"attribute": "purple", "score": 0.00082}, {"attribute": "brown", "score": 0.00072}, {"attribute": "canyon-rose", "score": 0.00059}, {"attribute": "navy", "score": 0.00057}, {"attribute": "blue", "score": 0.00032}, {"attribute": "coral", "score": 0.00018}, {"attribute": "yellow", "score": 0.00018}, {"attribute": "silver", "score": 0.00014}, {"attribute": "beige", "score": 0.00011}, {"attribute": "gold", "score": 8e-05}, {"attribute": "ecru", "score": 8e-05}, {"attribute": "emerald-green", "score": 6e-05}, {"attribute": "mustard", "score": 6e-05}, {"attribute": "orange", "score": 4e-05}, {"attribute": "copper", "score": 4e-05}, {"attribute": "lavander", "score": 3e-05}, {"attribute": "green", "score": 3e-05}, {"attribute": "khaki", "score": 2e-05}, {"attribute": "pastel", "score": 2e-05}, {"attribute": "turquoise", "score": 1e-05}, {"attribute": "neon", "score": 1e-05}, {"attribute": "mint", "score": 1e-05}]}}, {"attribute_type": "pattern", "attributes": {"correct": [{"attribute": "horizontal-stripes", "score": 0.9081}], "all": [{"attribute": "horizontal-stripes", "score": 0.9081}, {"attribute": "stripes", "score": 0.05544}, {"attribute": "chevron", "score": 0.01456}, {"attribute": "diagonal-stripes", "score": 0.01086}, {"attribute": "marled", "score": 0.00715}, {"attribute": "text-print", "score": 0.0011}, {"attribute": "geometric", "score": 0.00086}, {"attribute": "varsity-striped", "score": 0.00041}, {"attribute": "gingham", "score": 0.00024}, {"attribute": "ombre", "score": 0.00017}, {"attribute": "checkerboard", "score": 0.00017}, {"attribute": "shapes", "score": 0.00013}, {"attribute": "brush-stroke", "score": 0.00012}, {"attribute": "glitter", "score": 0.00011}, {"attribute": "net", "score": 6e-05}, {"attribute": "harlequin", "score": 6e-05}, {"attribute": "abstract", "score": 5e-05}, {"attribute": "plain", "score": 5e-05}, {"attribute": "dots", "score": 4e-05}, {"attribute": "vertical-stripes", "score": 4e-05}, {"attribute": "retro", "score": 3e-05}, {"attribute": "camo", "score": 3e-05}, {"attribute": "logo-print", "score": 3e-05}, {"attribute": "floral", "score": 3e-05}, {"attribute": "zebra", "score": 2e-05}, {"attribute": "bird's-eye", "score": 2e-05}, {"attribute": "quilted", "score": 2e-05}, {"attribute": "arrow-print", "score": 1e-05}, {"attribute": "greek-key", "score": 1e-05}, {"attribute": "herringbone", "score": 1e-05}, {"attribute": "sequined", "score": 1e-05}, {"attribute": "tartan", "score": 1e-05}, {"attribute": "3d-print", "score": 1e-05}, {"attribute": "windowpane", "score": 1e-05}, {"attribute": "bleached", "score": 1e-05}, {"attribute": "feathers", "score": 0.0}, {"attribute": "scale", "score": 0.0}, {"attribute": "brocade", "score": 0.0}, {"attribute": "houndstooth", "score": 0.0}, {"attribute": "damask", "score": 0.0}, {"attribute": "natural", "score": 0.0}, {"attribute": "fruits", "score": 0.0}, {"attribute": "paisley", "score": 0.0}, {"attribute": "graph-check", "score": 0.0}, {"attribute": "glen-check", "score": 0.0}, {"attribute": "crocodile-skin", "score": 0.0}, {"attribute": "snake-skin", "score": 0.0}, {"attribute": "animal-print", "score": 0.0}, {"attribute": "animals", "score": 0.0}, {"attribute": "leaf", "score": 0.0}]}}, {"attribute_type": "material", "attributes": {"correct": [], "all": [{"attribute": "teddy", "score": 0.0}, {"attribute": "cotton", "score": 0.0}, {"attribute": "knitted", "score": 0.0}, {"attribute": "linen", "score": 0.0}, {"attribute": "fur", "score": 0.0}, {"attribute": "leather", "score": 0.0}, {"attribute": "suede", "score": 0.0}, {"attribute": "tweed", "score": 0.0}, {"attribute": "velvet", "score": 0.0}, {"attribute": "satin", "score": 0.0}, {"attribute": "denim", "score": 0.0}, {"attribute": "canvas", "score": 0.0}, {"attribute": "chiffon", "score": 0.0}, {"attribute": "tulle", "score": 0.0}, {"attribute": "fuzzy", "score": 0.0}, {"attribute": "corduroy", "score": 0.0}, {"attribute": "silk", "score": 0.0}, {"attribute": "mesh", "score": 0.0}, {"attribute": "faux-fur", "score": 0.0}, {"attribute": "woven", "score": 0.0}, {"attribute": "crochet", "score": 0.0}, {"attribute": "lace", "score": 0.0}, {"attribute": "crinkled", "score": 0.0}]}}, {"attribute_type": "more_attributes", "attributes": {"correct": [], "all": [{"attribute": "draped", "score": 0.0}, {"attribute": "bib", "score": 0.0}, {"attribute": "open-back", "score": 0.0}, {"attribute": "pom-poms", "score": 0.0}, {"attribute": "wrap", "score": 0.0}, {"attribute": "slit", "score": 0.0}, {"attribute": "keyhole", "score": 0.0}, {"attribute": "lace-up", "score": 0.0}, {"attribute": "embroidered", "score": 0.0}, {"attribute": "ruched", "score": 0.0}, {"attribute": "cargo", "score": 0.0}, {"attribute": "knotted", "score": 0.0}, {"attribute": "stones", "score": 0.0}, {"attribute": "chains", "score": 0.0}, {"attribute": "fringe", "score": 0.0}, {"attribute": "ruffled", "score": 0.0}, {"attribute": "studs_and_spikes", "score": 0.0}, {"attribute": "pleated", "score": 0.0}, {"attribute": "pearls", "score": 0.0}, {"attribute": "jewels", "score": 0.0}, {"attribute": "ripped", "score": 0.0}, {"attribute": "drawstring", "score": 0.0}, {"attribute": "belted", "score": 0.0}, {"attribute": "zipper", "score": 0.0}, {"attribute": "shoelaces", "score": 0.0}, {"attribute": "buttons", "score": 0.0}, {"attribute": "metalic", "score": 0.0}]}}, {"attribute_type": "style", "attributes": {"correct": [{"attribute": "sporty", "score": 1.0}], "all": [{"attribute": "sporty", "score": 1.0}, {"attribute": "bohemian", "score": 0.0}, {"attribute": "business", "score": 0.0}, {"attribute": "casual", "score": 0.0}, {"attribute": "feminine", "score": 0.0}, {"attribute": "minimalism", "score": 0.0}, {"attribute": "modest", "score": 0.0}, {"attribute": "sexy", "score": 0.0}, {"attribute": "sophisticated", "score": 0.0}, {"attribute": "punk", "score": 0.0}]}}, {"attribute_type": "occasion", "attributes": {"correct": [{"attribute": "sport", "score": 1.0}], "all": [{"attribute": "sport", "score": 1.0}, {"attribute": "formal", "score": 0.0}, {"attribute": "semi-formal", "score": 0.0}, {"attribute": "office", "score": 0.0}, {"attribute": "nightout", "score": 0.0}, {"attribute": "dating", "score": 0.0}, {"attribute": "beach", "score": 0.0}, {"attribute": "casual", "score": 0.0}, {"attribute": "home-lounge", "score": 0.0}, {"attribute": "winter", "score": 0.0}, {"attribute": "summer", "score": 0.0}]}}]}], "meta": {"counter_products": 1}}}