{"raw": {"records": [{"_status": {"code": 200, "text": "OK", "request_id": "4ba59faf-ee10-4677-86c6-1da2cfb9fc27"}, "_id": "b141440b-c83c-4164-9475-c5ba5668bc8e", "_width": 1500, "_height": 2000, "_objects": [{"name": "Clothing", "id": "8e6cf45d-d416-4560-a89a-1b83b80e003b", "bound_box": [67, 944, 1075, 1993], "prob": 0.5736002922058105, "area": 0.352464, "Top Category": "Clothing", "_tags": {"Category": [{"prob": 0.99668, "name": "Clothing/Upper", "id": "fe984081-9c79-44ed-bf48-6e0075066e17"}], "Subcategory": [{"prob": 0.98234, "name": "tops", "id": "1bb9e272-64be-4d7e-9cae-318ab13a8d9b"}], "Color": [{"prob": 0.88718, "name": "pink", "id": "afa6233f-d92e-4582-af27-9d1296a9610a"}], "Cut": [{"prob": 0.99596, "name": "spaghetti straps", "id": "a4f3b867-4fee-458b-904b-5fdcacd5af13"}], "Gender": [{"prob": 0.99906, "name": "women", "id": "cc58c8ea-17a1-4caf-871b-3953a5ff4c3e"}], "Sleeves": [{"prob": 0.99836, "name": "sleeveless", "id": "d2bfd6a2-75c1-47b8-a590-3a50fea86424"}], "Material": [{"prob": 0.59285, "name": "cotton", "id": "adaf6cd0-2437-4fca-8c46-3ea8c5933bab"}], "Style": [{"prob": 0.49037, "name": "casual", "id": "f7c9e44d-1a33-46e8-94d5-0f7a7b3a274e"}, {"prob": 0.44861, "name": "sport", "id": "ff436d3d-09d7-4978-a9d0-2b6f41d2340c"}], "Age": [{"prob": 0.99113, "name": "adult", "id": "464f18b8-e61b-4f95-afe6-48b3a8db26ab"}], "Design": [{"prob": 0.9866, "name": "plain", "id": "ef9751c5-dfb9-4d36-9691-359865f8bb92"}], "Top Category": [{"id": "13052be8-2cc7-48e4-a782-a00d658f997c", "name": "Clothing", "prob": 1.0}]}, "_tags_simple": ["pink", "adult", "spaghetti straps", "plain", "women", "Clothing", "tops", "sleeveless", "Clothing/Upper", "cotton"], "Category": "Clothing/Upper"}, {"name": "Jewellery", "id": "76ab21a2-e393-4f40-8611-9f10d289a6c2", "bound_box": [332, 385, 424, 540], "prob": 0.3374783992767334, "area": 0.004753333333333333, "Top Category": "Jewellery", "_tags": {"Category": [{"prob": 0.50831, "name": "Jewellery/Earrings and Earcuffs", "id": "035a4c23-7026-4aa5-88e4-c3c1c1a3edb0"}, {"prob": 0.43642, "name": "Jewellery/Necklaces, Pendants and Chains", "id": "0d165b79-2c8f-4e39-b26d-179b1d7df6cf"}], "Color": [{"prob": 0.46196, "name": "rose gold", "id": "3a1deebc-e7b1-4ec4-9d6d-5907d5d5bd66"}, {"prob": 0.39985, "name": "yellow gold", "id": "4789a778-9789-4511-857e-b6d75b1fa95e"}], "Material": [{"prob": 0.92563, "name": "metal", "id": "c213f003-b8dc-41b2-8fdd-997b17ef12d3"}], "Gemstones": [{"prob": 0.9845, "name": "without gemstones", "id": "b4d88499-1d3c-4aff-a8dc-525c36c53e15"}], "Top Category": [{"id": "433cfa22-3d66-4999-85a1-2c067cb7d733", "name": "Jewellery", "prob": 1.0}]}, "_tags_simple": ["without gemstones", "Jewellery/Earrings and Earcuffs", "Jewellery", "metal"], "Category": "Jewellery/Earrings and Earcuffs"}]}], "version": "2022-02-23 09:30:33.780947+00:00", "model_format": "", "status": {"code": 200, "text": "OK", "request_id": "4ba59faf-ee10-4677-86c6-1da2cfb9fc27", "proc_id": "c89eb1b6-7c47-4753-b748-3c9bce02fac8"}, "statistics": {"processing time": 0.8413105010986328}}, "image": "https://fashion.coveodemo.com//images\\cn14725998.jpg", "clean": {"Clothing/Upper": {"Tags": ["pink", "adult", "spaghetti straps", "plain", "women", "Clothing", "tops", "sleeveless", "Clothing/Upper", "cotton"], "Category": "Clothing/Upper", "Subcategory": "tops", "Color": "pink", "Cut": "spaghetti straps", "Gender": "women", "Sleeves": "sleeveless", "Material": "cotton", "Style": "casual;sport", "Age": "adult", "Design": "plain", "Top Category": "Clothing", "ProductTitle": "Casual Pink Cotton Tops", "price": 22, "brand": "Ralph Lauren"}, "Jewellery/Earrings and Earcuffs": {"Tags": ["without gemstones", "Jewellery/Earrings and Earcuffs", "Jewellery", "metal"], "Category": "Jewellery/Earrings and Earcuffs", "Color": "rose gold;yellow gold", "Material": "metal", "Gemstones": "without gemstones", "Top Category": "Jewellery", "ProductTitle": " Rose Gold;Yellow Gold Metal ", "price": 14, "brand": "CMP"}}}