{"raw": {"records": [{"_status": {"code": 200, "text": "OK", "request_id": "6e0063ac-7126-4e46-acce-f4039376e8af"}, "_id": "380e9aea-484c-4b10-bbc2-77860bc6fee3", "_width": 1262, "_height": 1682, "_objects": [{"name": "Clothing", "id": "8e6cf45d-d416-4560-a89a-1b83b80e003b", "bound_box": [20, 12, 1197, 1677], "prob": 0.8332161903381348, "area": 0.9232203191808107, "Top Category": "Clothing", "_tags": {"Category": [{"prob": 0.92205, "name": "Clothing/Skirts", "id": "cc418058-260e-4526-978f-203749a94e23"}], "Color": [{"prob": 0.80695, "name": "purple and violet", "id": "3e1f7125-f736-43b0-a01a-6084e4d258cb"}], "Length": [{"prob": 0.85091, "name": "midi", "id": "9387bd7b-88b5-4fe8-bab2-d1bc79dd08df"}], "Style": [{"prob": 0.92966, "name": "casual", "id": "5118c51a-c340-4673-bd7b-b1d2f50f4e94"}], "Subcategory": [{"name": "casual skirts", "prob": 0.92205}, {"prob": 0.34557, "name": "mermaid skirts", "id": "bd3d2f98-1a3f-401e-a62b-db04cdaaacfd"}], "Material": [{"prob": 0.47766, "name": "cotton", "id": "adaf6cd0-2437-4fca-8c46-3ea8c5933bab"}], "Gender": [{"id": "cc58c8ea-17a1-4caf-871b-3953a5ff4c3e", "name": "women", "prob": 1.0}], "Design": [{"prob": 0.8037, "name": "melange", "id": "72a54b33-3e30-4a1c-bbaa-d05f45d0f381"}, {"prob": 0.3193, "name": "plain", "id": "ef9751c5-dfb9-4d36-9691-359865f8bb92"}], "Top Category": [{"id": "13052be8-2cc7-48e4-a782-a00d658f997c", "name": "Clothing", "prob": 1.0}]}, "_tags_simple": ["midi", "casual skirts", "casual", "Clothing", "melange", "women", "purple and violet", "Clothing/Skirts"], "Category": "Clothing/Skirts"}]}], "version": "2022-02-23 09:30:33.780947+00:00", "model_format": "", "status": {"code": 200, "text": "OK", "request_id": "6e0063ac-7126-4e46-acce-f4039376e8af", "proc_id": "3ac47a92-8781-477c-9149-444cccbdc354"}, "statistics": {"processing time": 0.5671861171722412}}, "image": "https://fashion.coveodemo.com//images\\cn14460185.jpg", "clean": {"Clothing/Skirts": {"Tags": ["midi", "casual skirts", "casual", "Clothing", "melange", "women", "purple and violet", "Clothing/Skirts"], "Category": "Clothing/Skirts", "Color": "purple and violet", "Length": "midi", "Style": "casual", "Subcategory": "casual skirts;mermaid skirts", "Material": "cotton", "Gender": "women", "Design": "melange;plain", "Top Category": "Clothing", "ProductTitle": "Casual Purple And Violet Cotton Casual Skirts", "price": 23, "brand": "Adidas"}}, "pixyle": {"status": "OK", "method": "autotag/image", "result": [{"product_id": "5515279", "category": "tank-top", "pixyle_detected_category": "tank-top", "verified": false, "score": 0.93, "product_coordinates": {"x_min": 0, "y_min": 0, "x_max": 1150, "y_max": 1540}, "detected_attributes_types": [{"attribute_type": "neckline_type", "attributes": {"correct": [{"attribute": "crew-neck", "score": 0.84895}], "all": [{"attribute": "crew-neck", "score": 0.84895}, {"attribute": "round-neck", "score": 0.10416}, {"attribute": "boat-neck", "score": 0.01971}, {"attribute": "high-neck", "score": 0.00945}, {"attribute": "one-shoulder", "score": 0.00425}, {"attribute": "v-neck", "score": 0.00354}, {"attribute": "shoulder-off", "score": 0.00322}, {"attribute": "square-neck", "score": 0.00206}, {"attribute": "sweetheart-neck", "score": 0.00172}, {"attribute": "cowl-neck", "score": 0.00111}, {"attribute": "turtle-neck", "score": 0.0006}, {"attribute": "round-v-neck", "score": 0.00045}, {"attribute": "polo", "score": 0.00037}, {"attribute": "cutaway", "score": 0.00016}, {"attribute": "button-down", "score": 9e-05}, {"attribute": "shawl-collar", "score": 6e-05}, {"attribute": "hooded", "score": 5e-05}, {"attribute": "notched-collar", "score": 4e-05}, {"attribute": "grandad", "score": 0.0}]}}, {"attribute_type": "tank_type", "attributes": {"correct": [{"attribute": "straps", "score": 0.55224}], "all": [{"attribute": "straps", "score": 0.55224}, {"attribute": "sleeveless", "score": 0.44776}]}}, {"attribute_type": "tops_fit", "attributes": {"correct": [{"attribute": "bodycon-tops", "score": 0.99706}], "all": [{"attribute": "bodycon-tops", "score": 0.99706}, {"attribute": "fitted-tops", "score": 0.00265}, {"attribute": "oversized-tops", "score": 0.00021}, {"attribute": "regular-fit-tops", "score": 8e-05}]}}, {"attribute_type": "tops_length", "attributes": {"correct": [{"attribute": "cropped", "score": 0.93633}], "all": [{"attribute": "cropped", "score": 0.93633}, {"attribute": "short", "score": 0.03418}, {"attribute": "thigh-length", "score": 0.02903}, {"attribute": "long", "score": 0.00046}]}}, {"attribute_type": "colors", "attributes": {"correct": [{"attribute": "purple", "score": 0.85341}], "all": [{"attribute": "purple", "score": 0.85341}, {"attribute": "lavander", "score": 0.13953}, {"attribute": "navy", "score": 0.0032}, {"attribute": "gold", "score": 0.00153}, {"attribute": "gray", "score": 0.00111}, {"attribute": "blue", "score": 0.00052}, {"attribute": "beige", "score": 0.00011}, {"attribute": "silver", "score": 9e-05}, {"attribute": "neon", "score": 9e-05}, {"attribute": "bordeaux", "score": 8e-05}, {"attribute": "white", "score": 4e-05}, {"attribute": "yellow", "score": 4e-05}, {"attribute": "coral", "score": 3e-05}, {"attribute": "pink", "score": 3e-05}, {"attribute": "khaki", "score": 3e-05}, {"attribute": "brown", "score": 2e-05}, {"attribute": "turquoise", "score": 2e-05}, {"attribute": "black", "score": 2e-05}, {"attribute": "mustard", "score": 2e-05}, {"attribute": "canyon-rose", "score": 2e-05}, {"attribute": "pastel", "score": 2e-05}, {"attribute": "multicolor", "score": 1e-05}, {"attribute": "red", "score": 1e-05}, {"attribute": "orange", "score": 1e-05}, {"attribute": "emerald-green", "score": 1e-05}, {"attribute": "ecru", "score": 1e-05}, {"attribute": "green", "score": 1e-05}, {"attribute": "magenta", "score": 0.0}, {"attribute": "copper", "score": 0.0}, {"attribute": "mint", "score": 0.0}]}}, {"attribute_type": "pattern", "attributes": {"correct": [{"attribute": "marled", "score": 0.97368}], "all": [{"attribute": "marled", "score": 0.97368}, {"attribute": "glitter", "score": 0.01155}, {"attribute": "plain", "score": 0.0065}, {"attribute": "ombre", "score": 0.00346}, {"attribute": "vertical-stripes", "score": 0.00189}, {"attribute": "stripes", "score": 0.00113}, {"attribute": "varsity-striped", "score": 0.00032}, {"attribute": "glen-check", "score": 0.00024}, {"attribute": "abstract", "score": 0.00023}, {"attribute": "bird's-eye", "score": 0.00015}, {"attribute": "bleached", "score": 0.00012}, {"attribute": "harlequin", "score": 0.00011}, {"attribute": "dots", "score": 9e-05}, {"attribute": "horizontal-stripes", "score": 9e-05}, {"attribute": "diagonal-stripes", "score": 8e-05}, {"attribute": "graph-check", "score": 5e-05}, {"attribute": "windowpane", "score": 4e-05}, {"attribute": "herringbone", "score": 3e-05}, {"attribute": "text-print", "score": 3e-05}, {"attribute": "damask", "score": 2e-05}, {"attribute": "chevron", "score": 2e-05}, {"attribute": "3d-print", "score": 2e-05}, {"attribute": "leaf", "score": 2e-05}, {"attribute": "arrow-print", "score": 1e-05}, {"attribute": "scale", "score": 1e-05}, {"attribute": "zebra", "score": 1e-05}, {"attribute": "sequined", "score": 1e-05}, {"attribute": "paisley", "score": 1e-05}, {"attribute": "quilted", "score": 1e-05}, {"attribute": "floral", "score": 1e-05}, {"attribute": "geometric", "score": 1e-05}, {"attribute": "shapes", "score": 1e-05}, {"attribute": "greek-key", "score": 0.0}, {"attribute": "feathers", "score": 0.0}, {"attribute": "brocade", "score": 0.0}, {"attribute": "retro", "score": 0.0}, {"attribute": "houndstooth", "score": 0.0}, {"attribute": "natural", "score": 0.0}, {"attribute": "brush-stroke", "score": 0.0}, {"attribute": "checkerboard", "score": 0.0}, {"attribute": "camo", "score": 0.0}, {"attribute": "net", "score": 0.0}, {"attribute": "fruits", "score": 0.0}, {"attribute": "gingham", "score": 0.0}, {"attribute": "logo-print", "score": 0.0}, {"attribute": "tartan", "score": 0.0}, {"attribute": "crocodile-skin", "score": 0.0}, {"attribute": "snake-skin", "score": 0.0}, {"attribute": "animal-print", "score": 0.0}, {"attribute": "animals", "score": 0.0}]}}, {"attribute_type": "material", "attributes": {"correct": [{"attribute": "linen", "score": 1.0}], "all": [{"attribute": "linen", "score": 1.0}, {"attribute": "teddy", "score": 0.0}, {"attribute": "cotton", "score": 0.0}, {"attribute": "knitted", "score": 0.0}, {"attribute": "fur", "score": 0.0}, {"attribute": "leather", "score": 0.0}, {"attribute": "suede", "score": 0.0}, {"attribute": "tweed", "score": 0.0}, {"attribute": "velvet", "score": 0.0}, {"attribute": "satin", "score": 0.0}, {"attribute": "denim", "score": 0.0}, {"attribute": "canvas", "score": 0.0}, {"attribute": "chiffon", "score": 0.0}, {"attribute": "tulle", "score": 0.0}, {"attribute": "fuzzy", "score": 0.0}, {"attribute": "corduroy", "score": 0.0}, {"attribute": "silk", "score": 0.0}, {"attribute": "mesh", "score": 0.0}, {"attribute": "faux-fur", "score": 0.0}, {"attribute": "woven", "score": 0.0}, {"attribute": "crochet", "score": 0.0}, {"attribute": "lace", "score": 0.0}, {"attribute": "crinkled", "score": 0.0}]}}, {"attribute_type": "more_attributes", "attributes": {"correct": [], "all": [{"attribute": "draped", "score": 0.0}, {"attribute": "bib", "score": 0.0}, {"attribute": "open-back", "score": 0.0}, {"attribute": "pom-poms", "score": 0.0}, {"attribute": "wrap", "score": 0.0}, {"attribute": "slit", "score": 0.0}, {"attribute": "keyhole", "score": 0.0}, {"attribute": "lace-up", "score": 0.0}, {"attribute": "embroidered", "score": 0.0}, {"attribute": "ruched", "score": 0.0}, {"attribute": "cargo", "score": 0.0}, {"attribute": "knotted", "score": 0.0}, {"attribute": "stones", "score": 0.0}, {"attribute": "chains", "score": 0.0}, {"attribute": "fringe", "score": 0.0}, {"attribute": "ruffled", "score": 0.0}, {"attribute": "studs_and_spikes", "score": 0.0}, {"attribute": "pleated", "score": 0.0}, {"attribute": "pearls", "score": 0.0}, {"attribute": "jewels", "score": 0.0}, {"attribute": "ripped", "score": 0.0}, {"attribute": "drawstring", "score": 0.0}, {"attribute": "belted", "score": 0.0}, {"attribute": "zipper", "score": 0.0}, {"attribute": "shoelaces", "score": 0.0}, {"attribute": "buttons", "score": 0.0}, {"attribute": "metalic", "score": 0.0}]}}, {"attribute_type": "style", "attributes": {"correct": [{"attribute": "casual", "score": 0.89814}], "all": [{"attribute": "casual", "score": 0.89814}, {"attribute": "sporty", "score": 0.09643}, {"attribute": "feminine", "score": 0.00543}, {"attribute": "minimalism", "score": 0.0}, {"attribute": "sexy", "score": 0.0}, {"attribute": "punk", "score": 0.0}, {"attribute": "bohemian", "score": 0.0}, {"attribute": "business", "score": 0.0}, {"attribute": "modest", "score": 0.0}, {"attribute": "sophisticated", "score": 0.0}]}}, {"attribute_type": "occasion", "attributes": {"correct": [{"attribute": "casual", "score": 0.89797}], "all": [{"attribute": "casual", "score": 0.89797}, {"attribute": "sport", "score": 0.09642}, {"attribute": "dating", "score": 0.00543}, {"attribute": "home-lounge", "score": 9e-05}, {"attribute": "summer", "score": 9e-05}, {"attribute": "nightout", "score": 0.0}, {"attribute": "formal", "score": 0.0}, {"attribute": "semi-formal", "score": 0.0}, {"attribute": "office", "score": 0.0}, {"attribute": "beach", "score": 0.0}, {"attribute": "winter", "score": 0.0}]}}]}], "meta": {"counter_products": 1}}}