{"raw": {"records": [{"_status": {"code": 200, "text": "OK", "request_id": "20dcd8c6-9862-49bb-98df-a987e8f94b35"}, "_id": "c6b81907-a0f8-4599-8638-5c977f4c8560", "_width": 1350, "_height": 1800, "_objects": [{"name": "Clothing", "id": "8e6cf45d-d416-4560-a89a-1b83b80e003b", "bound_box": [288, 835, 1052, 1773], "prob": 0.6389773488044739, "area": 0.29491028806584363, "Top Category": "Clothing", "_tags": {"Category": [{"prob": 0.68306, "name": "Clothing/Upper", "id": "fe984081-9c79-44ed-bf48-6e0075066e17"}], "Subcategory": [{"prob": 0.97049, "name": "shirts", "id": "0dc6dd93-817c-41b4-93c6-7a8a87283736"}], "Color": [{"prob": 0.85117, "name": "white", "id": "da5d452c-2534-4bb9-9e56-a1904c25ab0c"}], "Cut": [{"prob": 0.68734, "name": "strapless", "id": "ec177964-80fb-42c5-b633-58964e8cff07"}], "Gender": [{"prob": 0.7593, "name": "women", "id": "cc58c8ea-17a1-4caf-871b-3953a5ff4c3e"}], "Sleeves": [{"prob": 0.60585, "name": "3/4 sleeves", "id": "3f92ca9f-16a0-44a3-8b3c-fe10cf6e901d"}, {"prob": 0.35184, "name": "sleeveless", "id": "d2bfd6a2-75c1-47b8-a590-3a50fea86424"}], "Material": [{"prob": 0.75591, "name": "silk", "id": "16e1e984-4ae4-4843-9705-051364e13ecd"}], "Style": [{"prob": 0.73478, "name": "elegant", "id": "4fbfc71c-3134-4bfc-961e-bcd88d9170ab"}], "Age": [{"prob": 0.97388, "name": "adult", "id": "464f18b8-e61b-4f95-afe6-48b3a8db26ab"}], "Design": [{"prob": 0.86023, "name": "plain", "id": "ef9751c5-dfb9-4d36-9691-359865f8bb92"}], "Top Category": [{"id": "13052be8-2cc7-48e4-a782-a00d658f997c", "name": "Clothing", "prob": 1.0}]}, "_tags_simple": ["Clothing", "strapless", "3/4 sleeves", "elegant", "Clothing/Upper", "silk", "white", "women", "shirts", "plain", "adult"], "Category": "Clothing/Upper"}, {"name": "Clothing", "id": "8e6cf45d-d416-4560-a89a-1b83b80e003b", "bound_box": [400, 182, 955, 692], "prob": 0.5766438245773315, "area": 0.11648148148148148, "Top Category": "Clothing", "_tags": {"Category": [{"prob": 0.98498, "name": "Clothing/Upper", "id": "fe984081-9c79-44ed-bf48-6e0075066e17"}], "Subcategory": [{"prob": 0.98296, "name": "tops", "id": "1bb9e272-64be-4d7e-9cae-318ab13a8d9b"}, {"name": "crop tops", "prob": 0.77715}], "Color": [{"prob": 0.99525, "name": "black", "id": "9346545f-13e8-43c6-85b3-eab4a2319020"}], "Cut": [{"prob": 0.77715, "name": "shorted", "id": "5645b088-9bd5-430b-a997-6902d2979942"}, {"prob": 0.72563, "name": "spaghetti straps", "id": "a4f3b867-4fee-458b-904b-5fdcacd5af13"}], "Gender": [{"prob": 0.99414, "name": "women", "id": "cc58c8ea-17a1-4caf-871b-3953a5ff4c3e"}], "Neckline": [{"prob": 0.63003, "name": "low cut", "id": "27755591-d8de-4832-bdc7-531ad5be9297"}], "Sleeves": [{"prob": 0.99819, "name": "sleeveless", "id": "d2bfd6a2-75c1-47b8-a590-3a50fea86424"}], "Material": [{"prob": 0.86349, "name": "leather", "id": "a3242726-0995-43bf-9c53-6f75ca378112"}], "Style": [{"prob": 0.62274, "name": "casual", "id": "f7c9e44d-1a33-46e8-94d5-0f7a7b3a274e"}], "Age": [{"prob": 0.99405, "name": "adult", "id": "464f18b8-e61b-4f95-afe6-48b3a8db26ab"}], "Design": [{"prob": 0.82636, "name": "logo", "id": "646f8090-2edf-4c2e-b0ad-71edf9342ed3"}, {"prob": 0.41038, "name": "plain", "id": "ef9751c5-dfb9-4d36-9691-359865f8bb92"}], "Top Category": [{"id": "13052be8-2cc7-48e4-a782-a00d658f997c", "name": "Clothing", "prob": 1.0}]}, "_tags_simple": ["low cut", "casual", "Clothing", "leather", "Clothing/Upper", "logo", "shorted", "black", "crop tops", "tops", "spaghetti straps", "women", "adult", "sleeveless"], "Category": "Clothing/Upper"}]}], "version": "2022-02-23 09:30:33.780947+00:00", "model_format": "", "status": {"code": 200, "text": "OK", "request_id": "20dcd8c6-9862-49bb-98df-a987e8f94b35", "proc_id": "cb1a5e4d-5af6-4b7b-90c6-26da391578ee"}, "statistics": {"processing time": 0.8503243923187256}}, "image": "https://fashion.coveodemo.com//images\\cn14223998.jpg", "clean": {"Clothing/Upper": {"Tags": ["Clothing", "strapless", "3/4 sleeves", "elegant", "Clothing/Upper", "silk", "white", "women", "shirts", "plain", "adult"], "Category": "Clothing/Upper", "Subcategory": "shirts", "Color": "white", "Cut": "strapless", "Gender": "women", "Sleeves": "3/4 sleeves;sleeveless", "Material": "silk", "Style": "elegant", "Age": "adult", "Design": "plain", "Top Category": "Clothing", "ProductTitle": "Elegant White Silk Shirts", "price": 19, "brand": "Adidas"}}}